SpiderNet/__init__.py
SpiderNet/conn.py
SpiderNet/data_types/__init__.py
SpiderNet/data_types/d_types.py
SpiderNet/data_types/loops.py
SpiderNet-1.3.dist-info/METADATA
SpiderNet-1.3.dist-info/WHEEL
SpiderNet-1.3.dist-info/top_level.txt
SpiderNet-1.3.dist-info/RECORD
