Metadata-Version: 2.1
Name: SpiderNet
Version: 1.3
Summary: A python package to simplify web scraping . Built using REgex and Curl
Home-page: https://github.com/query-lang/SpiderWeb
Author: Vishal
Author-email: vishalvenkat2604@gmail.com
License: MIT
Keywords: conversion
Classifier: Development Status :: 3 - Alpha
Classifier: Intended Audience :: Developers
Classifier: License :: OSI Approved :: MIT License
Classifier: Programming Language :: Python :: 3
